gen_art_framework/__init__.py
gen_art_framework/cli.py
gen_art_framework/distributions.py
gen_art_framework/executor.py
gen_art_framework/py.typed
gen_art_framework/schema.py
gen_art_framework/examples/__init__.py
gen_art_framework/examples/circles.py
gen_art_framework/examples/flow_field.py
gen_art_framework-0.3.0.dist-info/METADATA
gen_art_framework-0.3.0.dist-info/WHEEL
gen_art_framework-0.3.0.dist-info/entry_points.txt
gen_art_framework-0.3.0.dist-info/licenses/LICENSE
gen_art_framework-0.3.0.dist-info/RECORD
