Metadata-Version: 2.4
Name: gen-art-framework
Version: 0.3.0
Summary: A framework for creating generative art with Python
Project-URL: Homepage, https://github.com/josh-gree/gen-art-framework
Project-URL: Repository, https://github.com/josh-gree/gen-art-framework
Project-URL: Issues, https://github.com/josh-gree/gen-art-framework/issues
Author-email: josh-gree <joshuadouglasgreenhalgh@gmail.com>
License-Expression: MIT
License-File: LICENSE
Keywords: art,creative-coding,generative-art,image-generation
Classifier: Development Status :: 3 - Alpha
Classifier: Intended Audience :: Developers
Classifier: Intended Audience :: Education
Classifier: License :: OSI Approved :: MIT License
Classifier: Operating System :: OS Independent
Classifier: Programming Language :: Python :: 3
Classifier: Programming Language :: Python :: 3.12
Classifier: Topic :: Artistic Software
Classifier: Topic :: Multimedia :: Graphics
Requires-Python: <3.13,>=3.12
Requires-Dist: click>=8.3.1
Requires-Dist: numpy>=2.4.0
Requires-Dist: pillow>=12.0.0
Requires-Dist: pyyaml>=6.0.3
Requires-Dist: scipy>=1.16.3
